durbango/__init__.py
durbango/feature_importance.py
durbango/filesystem.py
durbango/git_moments.py
durbango/id_pairs.py
durbango/lgbm_kfold.py
durbango/nb_utils.py
durbango/pd_utils.py
durbango/ps_aux.py
durbango/send_gmail.py
durbango/send_sms.py
durbango/shitty_utils.py
durbango/tensorboard_parser.py
durbango/test_email.py
durbango/test_utils.py
durbango-0.2.dist-info/LICENSE
durbango-0.2.dist-info/METADATA
durbango-0.2.dist-info/WHEEL
durbango-0.2.dist-info/top_level.txt
durbango-0.2.dist-info/RECORD
