Metadata-Version: 2.1
Name: durbango
Version: 0.2
Summary: Shortcuts for Matrix Wrangling
Home-page: UNKNOWN
Author: Sam Shleifer
Author-email: sshleifer@gmail.com
License: UNKNOWN
Platform: UNKNOWN
